{"_type":"export","__export_format":4,"__export_date":"2024-09-27T18:43:40.430Z","__export_source":"insomnia.desktop.app:v2022.7.5","resources":[{"_id":"req_23e9b1cc7efb487bbca30986a86ba31f","parentId":"wrk_92e863e4021049178340991bd9cdc9ef","modified":1727462018187,"created":1727461676657,"url":"127.0.0.1/api/carros/search","name":"modelo","description":"","method":"GET","body":{"mimeType":"application/json","text":"{\n\t\"veiculo\":\"carro\"\n}"},"parameters":[],"headers":[{"name":"Content-Type","value":"application/json"}],"authentication":{},"metaSortKey":-1727461676657,"isPrivate":false,"settingStoreCookies":true,"settingSendCookies":true,"settingDisableRenderRequestBody":false,"settingEncodeUrl":true,"settingRebuildPath":true,"settingFollowRedirects":"global","_type":"request"},{"_id":"wrk_92e863e4021049178340991bd9cdc9ef","parentId":null,"modified":1674483403822,"created":1674483403822,"name":"New Document","description":"","scope":"design","_type":"workspace"},{"_id":"req_ffba474564a342c2a32e96834bc2c23e","parentId":"wrk_92e863e4021049178340991bd9cdc9ef","modified":1727461542789,"created":1727461329705,"url":"127.0.0.1/api/carros/search","name":"marca","description":"","method":"GET","body":{"mimeType":"application/json","text":"{\n\t\"marca\": \"porche\"\n}"},"parameters":[],"headers":[{"name":"Content-Type","value":"application/json"}],"authentication":{},"metaSortKey":-1727461329705,"isPrivate":false,"settingStoreCookies":true,"settingSendCookies":true,"settingDisableRenderRequestBody":false,"settingEncodeUrl":true,"settingRebuildPath":true,"settingFollowRedirects":"global","_type":"request"},{"_id":"req_86b5a8e24d1440c6b483e7a5875b25de","parentId":"wrk_92e863e4021049178340991bd9cdc9ef","modified":1727461260286,"created":1727457808009,"url":"127.0.0.1/api/carros/1/find","name":"pesquisa/id","description":"","method":"GET","body":{"mimeType":"application/json","text":""},"parameters":[],"headers":[{"name":"Content-Type","value":"application/json"}],"authentication":{},"metaSortKey":-1727457808009,"isPrivate":false,"settingStoreCookies":true,"settingSendCookies":true,"settingDisableRenderRequestBody":false,"settingEncodeUrl":true,"settingRebuildPath":true,"settingFollowRedirects":"global","_type":"request"},{"_id":"req_70cc54c976ec4435bfbef1043e5f6991","parentId":"wrk_92e863e4021049178340991bd9cdc9ef","modified":1727455637924,"created":1727438724469,"url":"127.0.0.1/api/carro","name":"store","description":"","method":"POST","body":{"mimeType":"application/json","text":"{\n\t\"marca\": \"porche\",\n\t\"modelo\": \"A\",\n\t\"ano\":2005,\n\t\"placa\": \"aur0809\",\n\t\"veiculo\": \"carro\",\n\t\"venda\":\"15000.40\"\n}"},"parameters":[],"headers":[{"name":"Content-Type","value":"application/json"}],"authentication":{},"metaSortKey":-1727438724469,"isPrivate":false,"settingStoreCookies":true,"settingSendCookies":true,"settingDisableRenderRequestBody":false,"settingEncodeUrl":true,"settingRebuildPath":true,"settingFollowRedirects":"global","_type":"request"},{"_id":"req_36f91a5c0f1a43de826209678f07a74d","parentId":"wrk_92e863e4021049178340991bd9cdc9ef","modified":1727455110251,"created":1727438720318,"url":"127.0.0.1/api/carros","name":"index","description":"","method":"GET","body":{"mimeType":"application/json","text":"{\n\t\n}"},"parameters":[],"headers":[{"name":"Content-Type","value":"application/json"}],"authentication":{},"metaSortKey":-1727438720318,"isPrivate":false,"settingStoreCookies":true,"settingSendCookies":true,"settingDisableRenderRequestBody":false,"settingEncodeUrl":true,"settingRebuildPath":true,"settingFollowRedirects":"global","_type":"request"},{"_id":"req_e761f97dff6e4c228b21636f6287c7ef","parentId":"wrk_92e863e4021049178340991bd9cdc9ef","modified":1727456971676,"created":1727438718086,"url":"127.0.0.1/api/update","name":"update","description":"","method":"PUT","body":{"mimeType":"application/json","text":"{\n\t\"id\":2,\n\t\"modelo\":\"C\"\n}"},"parameters":[],"headers":[{"name":"Content-Type","value":"application/json"}],"authentication":{},"metaSortKey":-1727438718086,"isPrivate":false,"settingStoreCookies":true,"settingSendCookies":true,"settingDisableRenderRequestBody":false,"settingEncodeUrl":true,"settingRebuildPath":true,"settingFollowRedirects":"global","_type":"request"},{"_id":"req_643569000f7e46a8a79b33af5749b5a9","parentId":"wrk_92e863e4021049178340991bd9cdc9ef","modified":1727457798869,"created":1674483403831,"url":"127.0.0.1/api/carros/3/delete","name":"delete","description":"","method":"DELETE","body":{"mimeType":"application/json","text":"{\n\t\n}"},"parameters":[],"headers":[{"name":"Content-Type","value":"application/json"}],"authentication":{},"metaSortKey":-1674483403831,"isPrivate":false,"settingStoreCookies":true,"settingSendCookies":true,"settingDisableRenderRequestBody":false,"settingEncodeUrl":true,"settingRebuildPath":true,"settingFollowRedirects":"global","_type":"request"},{"_id":"env_345c9bd1a2912c8ecdd515437a154274cef216ec","parentId":"wrk_92e863e4021049178340991bd9cdc9ef","modified":1674483403826,"created":1674483403826,"name":"Base Environment","data":{},"dataPropertyOrder":null,"color":null,"isPrivate":false,"metaSortKey":1674483403826,"_type":"environment"},{"_id":"jar_345c9bd1a2912c8ecdd515437a154274cef216ec","parentId":"wrk_92e863e4021049178340991bd9cdc9ef","modified":1674483403827,"created":1674483403827,"name":"Default Jar","cookies":[],"_type":"cookie_jar"},{"_id":"spc_3f78eb2013b94aaf81b3cf226fcc46ae","parentId":"wrk_92e863e4021049178340991bd9cdc9ef","modified":1727438711211,"created":1674483403822,"fileName":"New Document","contents":"","contentType":"yaml","_type":"api_spec"},{"_id":"uts_1380377451c2487d95e3939bbc8a822b","parentId":"wrk_92e863e4021049178340991bd9cdc9ef","modified":1674483403833,"created":1674483403833,"name":"Example Test Suite","_type":"unit_test_suite"}]}